tortoise_pathway/__init__.py
tortoise_pathway/__main__.py
tortoise_pathway/cli.py
tortoise_pathway/field_ext.py
tortoise_pathway/generators.py
tortoise_pathway/index_ext.py
tortoise_pathway/migration.py
tortoise_pathway/migration_manager.py
tortoise_pathway/schema_differ.py
tortoise_pathway/state.py
tortoise_pathway/operations/__init__.py
tortoise_pathway/operations/add_field.py
tortoise_pathway/operations/add_index.py
tortoise_pathway/operations/alter_field.py
tortoise_pathway/operations/create_model.py
tortoise_pathway/operations/drop_field.py
tortoise_pathway/operations/drop_index.py
tortoise_pathway/operations/drop_model.py
tortoise_pathway/operations/operation.py
tortoise_pathway/operations/rename_field.py
tortoise_pathway/operations/rename_model.py
tortoise_pathway/operations/run_sql.py
tortoise_pathway/schema/__init__.py
tortoise_pathway/schema/base.py
tortoise_pathway/schema/postgres.py
tortoise_pathway/schema/sqlite.py
tortoise_pathway-0.2.1.dist-info/METADATA
tortoise_pathway-0.2.1.dist-info/WHEEL
tortoise_pathway-0.2.1.dist-info/entry_points.txt
tortoise_pathway-0.2.1.dist-info/licenses/LICENSE.txt
tortoise_pathway-0.2.1.dist-info/RECORD
