Metadata-Version: 2.4
Name: tortoise-pathway
Version: 0.2.1
Summary: A schema migration tool for Tortoise ORM
Project-URL: Homepage, https://github.com/henadzit/tortoise-pathway
Project-URL: Documentation, https://github.com/henadzit/tortoise-pathway
Project-URL: Repository, https://github.com/henadzit/tortoise-pathway.git
Project-URL: Issues, https://github.com/henadzit/tortoise-pathway/issues
Author: henadzit
License: Apache-2.0
License-File: LICENSE.txt
Classifier: Framework :: AsyncIO
Classifier: License :: OSI Approved :: Apache Software License
Classifier: Operating System :: MacOS :: MacOS X
Classifier: Operating System :: Microsoft :: Windows
Classifier: Operating System :: OS Independent
Classifier: Operating System :: POSIX
Classifier: Programming Language :: Python :: 3
Classifier: Topic :: Database
Classifier: Topic :: Software Development :: Libraries :: Python Modules
Requires-Python: >=3.12
Requires-Dist: tortoise-orm>=0.24.2
Provides-Extra: psycopg
Requires-Dist: psycopg[pool]>=3.2.6; extra == 'psycopg'
